lang_voter/__init__.py
lang_voter/config.py
lang_voter/model_loader.py
lang_voter/voter.py
lang_voter-0.1.0.dist-info/licenses/LICENSE
lang_voter-0.1.0.dist-info/METADATA
lang_voter-0.1.0.dist-info/WHEEL
lang_voter-0.1.0.dist-info/top_level.txt
lang_voter-0.1.0.dist-info/RECORD
